{"recipeName":"fake sourdough","publishedAt":"2024-03-03T01:07:16.525Z","author":"Head Chef Daisy","description":"here is a tasty recipe","prepTime":"5 mins","totalTime":"10 mins","totalYield":"1 egg","recipeIngredients":["2 eggs","4 cups of flour","3 cups of water","good!","2 eggs"],"recipeInstructions":[{"text":"To make the overnight sponge: Stir down your refrigerated starter, and remove 1 cup (227g). Note: This is a good opportunity to feed the remainder, if necessary.","image":null},{"text":"In a large bowl, stir together the 1 cup (227g) unfed starter, flour, sugar, and buttermilk.","image":"/images/couple-pizza.png"}],"images":{"hero":"/images/Yellow-Banana-Bread_Hero_0530.jpg","gallery":["/images/cinnamonrolls.jpeg","/images/HawaiianRolls1.jpeg","/images/Pretzels.jpeg"]}}